AutoCellDetect/CellDetection.py
AutoCellDetect/DetectionWInterface.py
AutoCellDetect/ResizeFactor.py
AutoCellDetect/SelectRegion.py
AutoCellDetect/__init__.py
AutoCellDetect-0.1.0.dist-info/LICENSE
AutoCellDetect-0.1.0.dist-info/METADATA
AutoCellDetect-0.1.0.dist-info/WHEEL
AutoCellDetect-0.1.0.dist-info/top_level.txt
AutoCellDetect-0.1.0.dist-info/RECORD
