Metadata-Version: 2.1
Name: AutoCellDetect
Version: 0.1.0
Summary: Automatic Cell Detection for Microscopic Images
Author: Kathleen De Key
Author-email: kkey35@gatech.edu
License-File: LICENSE
Requires-Dist: pandas
Requires-Dist: cv2
Requires-Dist: numpy
